gidappdata/__init__.py
gidappdata/cli/__init__.py
gidappdata/cli/create_datapack_skeleton.py
gidappdata/cli/pack_and_bin_and_py_data.py
gidappdata/cli/prebuilt_folders.json
gidappdata/cli/skeleton_tree.py
gidappdata/cli/tree_render.py
gidappdata/data/__init__.py
gidappdata/data/script_data.py
gidappdata/data/serialized_skeletons/[standard]_basic.json
gidappdata/standard_appdata/__init__.py
gidappdata/standard_appdata/appdata_provider_new.py
gidappdata/standard_appdata/appdata_storager.py
gidappdata/utility/__init__.py
gidappdata/utility/bridge_configparser.py
gidappdata/utility/exceptions.py
gidappdata/utility/extended_dotenv.py
gidappdata/utility/functions.py
gidappdata/utility/misc.py
gidappdata-0.1.17.dist-info/entry_points.txt
gidappdata-0.1.17.dist-info/LICENSE
gidappdata-0.1.17.dist-info/WHEEL
gidappdata-0.1.17.dist-info/METADATA
gidappdata-0.1.17.dist-info/RECORD
