Metadata-Version: 2.1
Name: gidappdata
Version: 0.1.17
Summary: GidAppData provides an Userdata deployment, with appdirs as backendend, but easy access to files saved there. Also provides an option to 'fake' deploy it while still developing
Home-page: https://github.com/Giddius/GidAppData
License: UNKNOWN
Author: Giddius
Classifier: License :: OSI Approved :: MIT License
Requires-Dist: click>=7.1.2
Requires-Dist: appdirs>=1.4.4
Requires-Dist: gidlogger>=0.1.8
Requires-Dist: python-dotenv>=0.15.0
Requires-Dist: checksumdir
